bistrot/__about__.py
bistrot/__init__.py
bistrot/__main__.py
bistrot/bistrot.py
bistrot-0.1.0a4.dist-info/METADATA
bistrot-0.1.0a4.dist-info/WHEEL
bistrot-0.1.0a4.dist-info/entry_points.txt
bistrot-0.1.0a4.dist-info/licenses/LICENSE
bistrot-0.1.0a4.dist-info/RECORD
