Metadata-Version: 2.1
Name: bistrot
Version: 0.1.0a4
Summary: A cli tool that makes any Python function an executable
Project-URL: Documentation, https://github.com/mattiadg/bistrot#readme
Project-URL: Issues, https://github.com/mattiadg/bistrot/issues
Project-URL: Source, https://github.com/mattiadg/bistrot
Author-email: Mattia Di Gangi <mattiadigangi@gmail.com>
License-Expression: MIT
License-File: LICENSE
Classifier: Development Status :: 4 - Beta
Classifier: Programming Language :: Python
Classifier: Programming Language :: Python :: 3.8
Classifier: Programming Language :: Python :: 3.9
Classifier: Programming Language :: Python :: 3.10
Classifier: Programming Language :: Python :: 3.11
Classifier: Programming Language :: Python :: Implementation :: CPython
Classifier: Programming Language :: Python :: Implementation :: PyPy
Requires-Python: <3.12,>=3.8
